cosmic_explorer_pro/__init__.py
cosmic_explorer_pro/server.py
cosmic_explorer_pro-0.1.0.dist-info/METADATA
cosmic_explorer_pro-0.1.0.dist-info/WHEEL
cosmic_explorer_pro-0.1.0.dist-info/entry_points.txt
cosmic_explorer_pro-0.1.0.dist-info/RECORD
