Metadata-Version: 2.4
Name: cosmic-explorer-pro
Version: 0.1.0
Summary: An incredibly cool space MCP with real-time data, space weather, exoplanet discovery, Mars rover feeds, and interactive space simulations!
Requires-Python: >=3.10
Requires-Dist: fastmcp>=2.0.0
